mockylla/__init__.py
mockylla/results.py
mockylla/row.py
mockylla/classes/__init__.py
mockylla/classes/metadata.py
mockylla/classes/scylladb.py
mockylla/classes/session.py
mockylla/classes/state.py
mockylla/classes/statements.py
mockylla/parser/__init__.py
mockylla/parser/alter.py
mockylla/parser/batch.py
mockylla/parser/create.py
mockylla/parser/delete.py
mockylla/parser/drop.py
mockylla/parser/index.py
mockylla/parser/insert.py
mockylla/parser/materialized_view.py
mockylla/parser/select.py
mockylla/parser/truncate.py
mockylla/parser/type.py
mockylla/parser/update.py
mockylla/parser/utils.py
mockylla-0.5.0.dist-info/METADATA
mockylla-0.5.0.dist-info/WHEEL
mockylla-0.5.0.dist-info/licenses/LICENSE
mockylla-0.5.0.dist-info/RECORD
