Metadata-Version: 2.4
Name: mockylla
Version: 0.5.0
Summary: A lightweight, in-memory mock for the ScyllaDB **Python** driver.
Project-URL: Homepage, https://github.com/GenLogs/mockylla
Project-URL: Documentation, https://github.com/GenLogs/mockylla
Project-URL: Repository, https://github.com/GenLogs/mockylla
License: MIT
License-File: LICENSE
Keywords: cassandra,mock,scylla,scylladb,testing
Classifier: Development Status :: 4 - Beta
Classifier: Intended Audience :: Developers
Classifier: License :: OSI Approved :: MIT License
Classifier: Programming Language :: Python :: 3
Classifier: Programming Language :: Python :: 3.8
Classifier: Programming Language :: Python :: 3.9
Classifier: Programming Language :: Python :: 3.10
Classifier: Programming Language :: Python :: 3.11
Classifier: Topic :: Software Development :: Testing :: Mocking
Requires-Python: <3.12,>=3.8
Requires-Dist: scylla-driver
Provides-Extra: dev
Requires-Dist: complexipy>=3.1.0; extra == 'dev'
Requires-Dist: pytest>=7.0.1; extra == 'dev'
Requires-Dist: ruff>=0.0.17; extra == 'dev'
